sptext/__init__.py
sptext-1.1.3.dist-info/LICENSE
sptext-1.1.3.dist-info/METADATA
sptext-1.1.3.dist-info/WHEEL
sptext-1.1.3.dist-info/top_level.txt
sptext-1.1.3.dist-info/RECORD
