Metadata-Version: 2.1
Name: sptext
Version: 1.1.3
Summary: sptext
Home-page: UNKNOWN
Author: Ron AOV
Author-email: ronlatoiday@gmail.com
License: MIT
Platform: UNKNOWN
Classifier: Programming Language :: Python :: 3
Classifier: License :: OSI Approved :: MIT License
Requires-Python: >=3.6
License-File: LICENSE
